konvo/__init__.py
konvo/client.py
konvo-0.0.4.dist-info/METADATA
konvo-0.0.4.dist-info/WHEEL
konvo-0.0.4.dist-info/entry_points.txt
konvo-0.0.4.dist-info/RECORD
