Metadata-Version: 2.4
Name: konvo
Version: 0.0.4
Summary: Konvotech Python Package
Author-email: Berat Çimen <47108366+beratcmn@users.noreply.github.com>
Requires-Python: >=3.10
Requires-Dist: importlib-metadata>=8.5.0
Requires-Dist: requests>=2.32.3
